fastapi_opinionated/__init__.py
fastapi_opinionated/app.py
fastapi_opinionated/cli/__init__.py
fastapi_opinionated/cli/commands/__init__.py
fastapi_opinionated/cli/commands/list.py
fastapi_opinionated/cli/commands/new.py
fastapi_opinionated/cli/commands/plugins.py
fastapi_opinionated/cli/main.py
fastapi_opinionated/decorators/__init__.py
fastapi_opinionated/decorators/app_cmd.py
fastapi_opinionated/decorators/routing.py
fastapi_opinionated/exceptions/plugin_exception.py
fastapi_opinionated/registry/__init__.py
fastapi_opinionated/registry/plugin.py
fastapi_opinionated/registry/plugin_store.py
fastapi_opinionated/routing/__init__.py
fastapi_opinionated/routing/controller.py
fastapi_opinionated/routing/registry.py
fastapi_opinionated/shared/__init__.py
fastapi_opinionated/shared/base_plugin.py
fastapi_opinionated/shared/enabled_plugins.py
fastapi_opinionated/shared/logger.py
fastapi_opinionated/shared/response_formatter.py
fastapi_opinionated/utils/__init__.py
fastapi_opinionated/utils/import_string.py
fastapi_opinionated_core-0.1.2.dist-info/METADATA
fastapi_opinionated_core-0.1.2.dist-info/WHEEL
fastapi_opinionated_core-0.1.2.dist-info/entry_points.txt
fastapi_opinionated_core-0.1.2.dist-info/RECORD
