Metadata-Version: 2.3
Name: fastapi-opinionated-core
Version: 0.1.2
Summary: 
Author: Azzarnuji
Author-email: azzarnuzy93@gmail.com
Requires-Python: >=3.12
Classifier: Programming Language :: Python :: 3
Classifier: Programming Language :: Python :: 3.12
Classifier: Programming Language :: Python :: 3.13
Requires-Dist: fastapi[all] (>=0.121.1,<0.122.0)
